Workbook
Name Slicer_Category: #N/A
Name Slicer_Discount: #N/A
Name Slicer_Month2: #N/A
Name Slicer_Product_Name: #N/A
Name Slicer_Region: #N/A
Name Slicer_Total_Sales: #N/A
Name Slicer_Year: #N/A

Sheet Sheet2
A3: Product_Name | B3: City | C3: Sum of Discount_% | D3: Sum of Quantity | E3: Sum of Total_Sales
A4: Jacket | B4: Chennai | C4: 5 | D4: 1 | E4: 3240.08
A5: Jacket Total | C5: 5 | D5: 1 | E5: 3240.08
A7: Grand Total | C7: 5 | D7: 1 | E7: 3240.08

Sheet Raw Data
A1: Product_Name | B1: Category | C1: Brand | D1: Brand_Type | E1: Region | F1: City | G1: Unit_Price | H1: Discount_% | I1: Final_Unit_Price | J1: Quantity | K1: Total_Sales | L1: Profit | M1: Order_Date | N1: Delivery_Date
A2: Sneakers | B2: Footwear | C2: Puma | D2: Standard | E2: South | F2: Bengaluru | G2: 2514.6 | H2: 0 | I2: 2514.6 | J2: 2 | K2: 5029.2 | L2: 1257.3 | M2: 45521 | N2: 45525
A3: Coffee Table | B3: Furniture | C3: Godrej Interio | D3: Premium | E3: North | F3: Delhi | G3: 9954.58 | H3: 20 | I3: 7963.664 | J3: 4 | K3: 31854.66 | L3: 11149.13 | M3: 45382 | N3: 45386
A4: Laptop | B4: Electronics | C4: Samsung | D4: Premium | E4: North | F4: Jaipur | G4: 61044.5 | H4: 5 | I4: 57992.275 | J4: 1 | K4: 57992.27 | L4: 20297.29 | M4: 45481 | N4: 45489
A5: Headphones | B5: Electronics | C5: Dell | D5: Standard | E5: East | F5: Bhubaneswar | G5: 1933.16 | H5: 10 | I5: 1739.844 | J5: 5 | K5: 8699.22 | L5: 2174.8 | M5: 45429 | N5: 45432
A6: Bed | B6: Furniture | C6: Ikea | D6: Premium | E6: East | F6: Bhubaneswar | G6: 33576.85 | H6: 30 | I6: 23503.795 | J6: 3 | K6: 70511.38 | L6: 24678.98 | M6: 45363 | N6: 45365
A7: Jacket | B7: Clothing | C7: Max | D7: Budget | E7: North | F7: Jaipur | G7: 2617.88 | H7: 20 | I7: 2094.304 | J7: 3 | K7: 6282.91 | L7: 942.44 | M7: 45781 | N7: 45791
A8: Coffee Table | B8: Furniture | C8: Ikea | D8: Premium | E8: North | F8: Lucknow | G8: 10447.25 | H8: 0 | I8: 10447.25 | J8: 4 | K8: 41789 | L8: 14626.15 | M8: 45798 | N8: 45805
A9: Formal Shoes | B9: Footwear | C9: Bata | D9: Budget | E9: South | F9: Hyderabad | G9: 2887.51 | H9: 15 | I9: 2454.3835 | J9: 2 | K9: 4908.77 | L9: 736.32 | M9: 45537 | N9: 45541
A10: Refrigerator | B10: Home Appliance | C10: Samsung | D10: Premium | E10: South | F10: Hyderabad | G10: 28339.06 | H10: 5 | I10: 26922.107 | J10: 2 | K10: 53844.21 | L10: 18845.47 | M10: 45858 | N10: 45868
A11: Refrigerator | B11: Home Appliance | C11: Samsung | D11: Premium | E11: South | F11: Chennai | G11: 29172.62 | H11: 20 | I11: 23338.096 | J11: 4 | K11: 93352.38 | L11: 32673.33 | M11: 45660 | N11: 45664
A12: Dining Table | B12: Furniture | C12: HomeTown | D12: Standard | E12: East | F12: Bhubaneswar | G12: 22864.48 | H12: 20 | I12: 18291.584 | J12: 2 | K12: 36583.17 | L12: 9145.79 | M12: 45729 | N12: 45732
A13: Refrigerator | B13: Home Appliance | C13: Godrej | D13: Budget | E13: South | F13: Hyderabad | G13: 21784.17 | H13: 30 | I13: 15248.919 | J13: 1 | K13: 15248.92 | L13: 2287.34 | M13: 45854 | N13: 45857
... A1201: Refrigerator | B1201: Home Appliance | C1201: Godrej | D1201: Budget | E1201: North | F1201: Delhi | G1201: 22650.2 | H1201: 15 | I1201: 19252.67 | J1201: 1 | K1201: 19252.67 | L1201: 2887.9 | M1201: 45853 | N1201: 45863

Sheet Sheet1
A3: Row Labels | B3: Count of ProductID
A4: Bed | B4: 4
A5: Coffee Table | B5: 4 | E5: Row Labels | F5: Count of ProductID
A6: Dining Table | B6: 4 | E6: Bed | F6: 4
A7: Formal Shoes | B7: 3 | E7: Coffee Table | F7: 4
A8: Headphones | B8: 6 | E8: Dining Table | F8: 4
A9: Jacket | B9: 6 | E9: Formal Shoes | F9: 3
A10: Jeans | B10: 6 | E10: Headphones | F10: 6
A11: Laptop | B11: 6 | E11: Jacket | F11: 6
A12: Microwave | B12: 4 | E12: Jeans | F12: 6
A13: Refrigerator | B13: 4 | E13: Laptop | F13: 6
A14: Smartphone | B14: 6 | E14: Microwave | F14: 4
A15: Sneakers | B15: 3 | E15: Refrigerator | F15: 4
A16: Sofa Set | B16: 4 | E16: Smartphone | F16: 6
A17: T-Shirt | B17: 6 | E17: Sneakers | F17: 3
... A19: Grand Total | B19: 70 | E19: T-Shirt | F19: 6
E20: Washing Machine | F20: 4
E21: Grand Total | F21: 70

Sheet Master Table
A1: ProductID | B1: Category | C1: Product | D1: Brand | E1: Brand Type
A2: P001 | B2: Clothing | C2: Jeans | D2: Max | E2: Budget | H2: Region
A3: P002 | B3: Clothing | C3: Jeans | D3: Roadster | E3: Budget | H3: East | I3: West | J3: North | K3: South
A4: P003 | B4: Clothing | C4: Jeans | D4: H&M | E4: Standard | G4: Cities | H4: Kolkata | I4: Mumbai | J4: Delhi | K4: Bengaluru
A5: P004 | B5: Clothing | C5: Jeans | D5: Zara | E5: Premium | H5: Bhubaneswar | I5: Ahmedabad | J5: Jaipur | K5: Chennai
A6: P005 | B6: Clothing | C6: Jeans | D6: Levis | E6: Premium | H6: Patna | I6: Pune | J6: Lucknow | K6: Hyderabad
A7: P006 | B7: Clothing | C7: Jeans | D7: Nike | E7: Premium
A8: P007 | B8: Clothing | C8: Jacket | D8: Max | E8: Budget
A9: P008 | B9: Clothing | C9: Jacket | D9: Roadster | E9: Budget
A10: P009 | B10: Clothing | C10: Jacket | D10: H&M | E10: Standard
A11: P010 | B11: Clothing | C11: Jacket | D11: Zara | E11: Premium
A12: P011 | B12: Clothing | C12: Jacket | D12: Levis | E12: Premium
A13: P012 | B13: Clothing | C13: Jacket | D13: Nike | E13: Premium
A14: P013 | B14: Clothing | C14: T-Shirt | D14: Max | E14: Budget
A15: P014 | B15: Clothing | C15: T-Shirt | D15: Roadster | E15: Budget
A16: P015 | B16: Clothing | C16: T-Shirt | D16: H&M | E16: Standard
A17: P016 | B17: Clothing | C17: T-Shirt | D17: Zara | E17: Premium
A18: P017 | B18: Clothing | C18: T-Shirt | D18: Levis | E18: Premium
... A71: P070 | B71: Home Appliance | C71: Washing Machine | D71: LG | E71: Premium

Sheet Cleaned Data
A1: Order_ID | B1: Product_Name | C1: Category | D1: Brand | E1: Brand_Type | F1: Region | G1: City | H1: Unit_Price | I1: Discount_% | J1: Final_Unit_Price | K1: Quantity | L1: Total_Sales | M1: Profit | N1: Order_Date | O1: Month2 | P1: Year | Q1: Delivery_Date | R1: Days_to_Deliver | S1: Season
A2: O-0001 | B2: Sneakers | C2: Footwear | D2: Puma | E2: Standard | F2: South | G2: Bengaluru | H2: 2514.6 | I2: 0 | J2: 2514.6 | K2: 20 | L2: =Table1[[#This Row],[Final_Unit_Price]]*Table1[[#This Row],[Quantity]] -> 50292 | M2: 1257.3 | N2: 45521 | O2: =TEXT(Table1[[#This Row],[Order_Date]],"mmm") -> Aug | P2: =YEAR(N2) -> 2024 | Q2: 45525 | R2: ='Cleaned Data'!$Q2-'Cleaned Data'!$N2 -> 4 | S2: =IF(OR(O2="Feb",O2="Mar",O2="Apr",O2="May"),"Summer", IF(OR(O2="Jun",O2="Jul",O2="Aug",O2="Sep"),"Monsoon", IF(OR(O2="Oct",O2="Nov",O2="Dec",O2= "Jan"),"Winter","Invalid"))) -> Monsoon
A3: O-0002 | B3: Coffee Table | C3: Furniture | D3: Godrej Interio | E3: Premium | F3: North | G3: Delhi | H3: 9954.58 | I3: 0.2 | J3: 7963.664 | K3: 4 | L3: =Table1[[#This Row],[Final_Unit_Price]]*Table1[[#This Row],[Quantity]] -> 31854.656 | M3: 11149.13 | N3: 45382 | O3: =TEXT(Table1[[#This Row],[Order_Date]],"mmm") -> Mar | P3: =YEAR(N3) -> 2024 | Q3: 45386 | R3: ='Cleaned Data'!$Q3-'Cleaned Data'!$N3 -> 4 | S3: =IF(OR(O3="Feb",O3="Mar",O3="Apr",O3="May"),"Summer", IF(OR(O3="Jun",O3="Jul",O3="Aug",O3="Sep"),"Monsoon", IF(OR(O3="Oct",O3="Nov",O3="Dec",O3= "Jan"),"Winter","Invalid"))) -> Summer
A4: O-0003 | B4: Laptop | C4: Electronics | D4: Samsung | E4: Premium | F4: North | G4: Jaipur | H4: 61044.5 | I4: 0.05 | J4: 57992.275 | K4: 1 | L4: =Table1[[#This Row],[Final_Unit_Price]]*Table1[[#This Row],[Quantity]] -> 57992.275 | M4: 20297.29 | N4: 45481 | O4: =TEXT(Table1[[#This Row],[Order_Date]],"mmm") -> Jul | P4: =YEAR(N4) -> 2024 | Q4: 45489 | R4: ='Cleaned Data'!$Q4-'Cleaned Data'!$N4 -> 8 | S4: =IF(OR(O4="Feb",O4="Mar",O4="Apr",O4="May"),"Summer", IF(OR(O4="Jun",O4="Jul",O4="Aug",O4="Sep"),"Monsoon", IF(OR(O4="Oct",O4="Nov",O4="Dec",O4= "Jan"),"Winter","Invalid"))) -> Monsoon
A5: O-0004 | B5: Headphones | C5: Electronics | D5: Dell | E5: Standard | F5: East | G5: Bhubaneswar | H5: 1933.16 | I5: 0.1 | J5: 1739.844 | K5: 5 | L5: =Table1[[#This Row],[Final_Unit_Price]]*Table1[[#This Row],[Quantity]] -> 8699.22 | M5: 2174.8 | N5: 45429 | O5: =TEXT(Table1[[#This Row],[Order_Date]],"mmm") -> May | P5: =YEAR(N5) -> 2024 | Q5: 45432 | R5: ='Cleaned Data'!$Q5-'Cleaned Data'!$N5 -> 3 | S5: =IF(OR(O5="Feb",O5="Mar",O5="Apr",O5="May"),"Summer", IF(OR(O5="Jun",O5="Jul",O5="Aug",O5="Sep"),"Monsoon", IF(OR(O5="Oct",O5="Nov",O5="Dec",O5= "Jan"),"Winter","Invalid"))) -> Summer
A6: O-0005 | B6: Bed | C6: Furniture | D6: Ikea | E6: Premium | F6: East | G6: Bhubaneswar | H6: 33576.85 | I6: 0.3 | J6: 23503.795 | K6: 3 | L6: =Table1[[#This Row],[Final_Unit_Price]]*Table1[[#This Row],[Quantity]] -> 70511.385 | M6: 24678.98 | N6: 45363 | O6: =TEXT(Table1[[#This Row],[Order_Date]],"mmm") -> Mar | P6: =YEAR(N6) -> 2024 | Q6: 45365 | R6: ='Cleaned Data'!$Q6-'Cleaned Data'!$N6 -> 2 | S6: =IF(OR(O6="Feb",O6="Mar",O6="Apr",O6="May"),"Summer", IF(OR(O6="Jun",O6="Jul",O6="Aug",O6="Sep"),"Monsoon", IF(OR(O6="Oct",O6="Nov",O6="Dec",O6= "Jan"),"Winter","Invalid"))) -> Summer
A7: O-0006 | B7: Jacket | C7: Clothing | D7: Max | E7: Budget | F7: North | G7: Jaipur | H7: 2617.88 | I7: 0.2 | J7: 2094.304 | K7: 3 | L7: =Table1[[#This Row],[Final_Unit_Price]]*Table1[[#This Row],[Quantity]] -> 6282.912 | M7: 942.44 | N7: 45781 | O7: =TEXT(Table1[[#This Row],[Order_Date]],"mmm") -> May | P7: =YEAR(N7) -> 2025 | Q7: 45791 | R7: ='Cleaned Data'!$Q7-'Cleaned Data'!$N7 -> 10 | S7: =IF(OR(O7="Feb",O7="Mar",O7="Apr",O7="May"),"Summer", IF(OR(O7="Jun",O7="Jul",O7="Aug",O7="Sep"),"Monsoon", IF(OR(O7="Oct",O7="Nov",O7="Dec",O7= "Jan"),"Winter","Invalid"))) -> Summer
A8: O-0007 | B8: Coffee Table | C8: Furniture | D8: Ikea | E8: Premium | F8: North | G8: Lucknow | H8: 10447.25 | I8: 0 | J8: 10447.25 | K8: 4 | L8: =Table1[[#This Row],[Final_Unit_Price]]*Table1[[#This Row],[Quantity]] -> 41789 | M8: 14626.15 | N8: 45798 | O8: =TEXT(Table1[[#This Row],[Order_Date]],"mmm") -> May | P8: =YEAR(N8) -> 2025 | Q8: 45805 | R8: ='Cleaned Data'!$Q8-'Cleaned Data'!$N8 -> 7 | S8: =IF(OR(O8="Feb",O8="Mar",O8="Apr",O8="May"),"Summer", IF(OR(O8="Jun",O8="Jul",O8="Aug",O8="Sep"),"Monsoon", IF(OR(O8="Oct",O8="Nov",O8="Dec",O8= "Jan"),"Winter","Invalid"))) -> Summer
A9: O-0008 | B9: Formal Shoes | C9: Footwear | D9: Bata | E9: Budget | F9: South | G9: Hyderabad | H9: 2887.51 | I9: 0.15 | J9: 2454.3835 | K9: 20 | L9: =Table1[[#This Row],[Final_Unit_Price]]*Table1[[#This Row],[Quantity]] -> 49087.67 | M9: 736.32 | N9: 45537 | O9: =TEXT(Table1[[#This Row],[Order_Date]],"mmm") -> Sep | P9: =YEAR(N9) -> 2024 | Q9: 45541 | R9: ='Cleaned Data'!$Q9-'Cleaned Data'!$N9 -> 4 | S9: =IF(OR(O9="Feb",O9="Mar",O9="Apr",O9="May"),"Summer", IF(OR(O9="Jun",O9="Jul",O9="Aug",O9="Sep"),"Monsoon", IF(OR(O9="Oct",O9="Nov",O9="Dec",O9= "Jan"),"Winter","Invalid"))) -> Monsoon
A10: O-0009 | B10: Refrigerator | C10: Home Appliance | D10: Samsung | E10: Premium | F10: South | G10: Hyderabad | H10: 28339.06 | I10: 0.05 | J10: 26922.107 | K10: 2 | L10: =Table1[[#This Row],[Final_Unit_Price]]*Table1[[#This Row],[Quantity]] -> 53844.214 | M10: 18845.47 | N10: 45858 | O10: =TEXT(Table1[[#This Row],[Order_Date]],"mmm") -> Jul | P10: =YEAR(N10) -> 2025 | Q10: 45868 | R10: ='Cleaned Data'!$Q10-'Cleaned Data'!$N10 -> 10 | S10: =IF(OR(O10="Feb",O10="Mar",O10="Apr",O10="May"),"Summer", IF(OR(O10="Jun",O10="Jul",O10="Aug",O10="Sep"),"Monsoon", IF(OR(O10="Oct",O10="Nov",O10="Dec",O10= "Jan"),"Winter","Invalid"))) -> Monsoon
A11: O-0010 | B11: Refrigerator | C11: Home Appliance | D11: Samsung | E11: Premium | F11: South | G11: Chennai | H11: 29172.62 | I11: 0.2 | J11: 23338.096 | K11: 4 | L11: =Table1[[#This Row],[Final_Unit_Price]]*Table1[[#This Row],[Quantity]] -> 93352.384 | M11: 32674.33 | N11: 45660 | O11: =TEXT(Table1[[#This Row],[Order_Date]],"mmm") -> Jan | P11: =YEAR(N11) -> 2025 | Q11: 45664 | R11: ='Cleaned Data'!$Q11-'Cleaned Data'!$N11 -> 4 | S11: =IF(OR(O11="Feb",O11="Mar",O11="Apr",O11="May"),"Summer", IF(OR(O11="Jun",O11="Jul",O11="Aug",O11="Sep"),"Monsoon", IF(OR(O11="Oct",O11="Nov",O11="Dec",O11= "Jan"),"Winter","Invalid"))) -> Winter
A12: O-0011 | B12: Dining Table | C12: Furniture | D12: HomeTown | E12: Standard | F12: East | G12: Bhubaneswar | H12: 22864.48 | I12: 0.2 | J12: 18291.584 | K12: 2 | L12: =Table1[[#This Row],[Final_Unit_Price]]*Table1[[#This Row],[Quantity]] -> 36583.168 | M12: 9145.79 | N12: 45729 | O12: =TEXT(Table1[[#This Row],[Order_Date]],"mmm") -> Mar | P12: =YEAR(N12) -> 2025 | Q12: 45732 | R12: ='Cleaned Data'!$Q12-'Cleaned Data'!$N12 -> 3 | S12: =IF(OR(O12="Feb",O12="Mar",O12="Apr",O12="May"),"Summer", IF(OR(O12="Jun",O12="Jul",O12="Aug",O12="Sep"),"Monsoon", IF(OR(O12="Oct",O12="Nov",O12="Dec",O12= "Jan"),"Winter","Invalid"))) -> Summer
A13: O-0012 | B13: Refrigerator | C13: Home Appliance | D13: Godrej | E13: Budget | F13: South | G13: Hyderabad | H13: 21784.17 | I13: 0.3 | J13: 15248.919 | K13: 1 | L13: =Table1[[#This Row],[Final_Unit_Price]]*Table1[[#This Row],[Quantity]] -> 15248.919 | M13: 2287.34 | N13: 45854 | O13: =TEXT(Table1[[#This Row],[Order_Date]],"mmm") -> Jul | P13: =YEAR(N13) -> 2025 | Q13: 45857 | R13: ='Cleaned Data'!$Q13-'Cleaned Data'!$N13 -> 3 | S13: =IF(OR(O13="Feb",O13="Mar",O13="Apr",O13="May"),"Summer", IF(OR(O13="Jun",O13="Jul",O13="Aug",O13="Sep"),"Monsoon", IF(OR(O13="Oct",O13="Nov",O13="Dec",O13= "Jan"),"Winter","Invalid"))) -> Monsoon
... A1201: O-1200 | B1201: Refrigerator | C1201: Home Appliance | D1201: Godrej | E1201: Budget | F1201: North | G1201: Delhi | H1201: 22650.2 | I1201: 0.15 | J1201: 19252.67 | K1201: 1 | L1201: =Table1[[#This Row],[Final_Unit_Price]]*Table1[[#This Row],[Quantity]] -> 19252.67 | M1201: 2887.9 | N1201: 45853 | O1201: =TEXT(Table1[[#This Row],[Order_Date]],"mmm") -> Jul | P1201: =YEAR(N1201) -> 2025 | Q1201: 45863 | R1201: ='Cleaned Data'!$Q1201-'Cleaned Data'!$N1201 -> 10 | S1201: =IF(OR(O1201="Feb",O1201="Mar",O1201="Apr",O1201="May"),"Summer", IF(OR(O1201="Jun",O1201="Jul",O1201="Aug",O1201="Sep"),"Monsoon", IF(OR(O1201="Oct",O1201="Nov",O1201="Dec",O1201= "Jan"),"Winter","Invalid"))) -> Monsoon

Sheet Order Record
B2: Enter Record No: | E2: 0001 | G2: Order ID: | H2: =CONCATENATE("O-",E2) -> O-0001
C6: Category: | D6: =VLOOKUP($H$2,'Cleaned Data'!A:L,3,0) -> Footwear | F6: Order Date: | H6: =INDEX('Cleaned Data'!N:N,MATCH($H$2,'Cleaned Data'!A:A,0)) -> 45521
C7: Brand: | D7: =CONCATENATE(VLOOKUP($H$2,'Cleaned Data'!A:L,4,0)," ","(",VLOOKUP($H$2,'Cleaned Data'!A:L,5,0),")") -> Puma (Standard) | F7: Delivery Date: | H7: =INDEX('Cleaned Data'!Q:Q,MATCH($H$2,'Cleaned Data'!A:A,0)) -> 45525
C8: Region: | D8: =VLOOKUP($H$2,'Cleaned Data'!A:L,6,0) -> South
C9: City: | D9: =VLOOKUP($H$2,'Cleaned Data'!A:L,7,0) -> Bengaluru
C11: Product Name | E11: Unit Price | F11: Quantity | G11: Amount
C12: =VLOOKUP($H$2,'Cleaned Data'!A:L,2,0) -> Sneakers | E12: =VLOOKUP($H$2,'Cleaned Data'!A:L,8,0) -> 2514.6 | F12: =VLOOKUP($H$2,'Cleaned Data'!A:L,11,0) -> 20 | G12: ='Order Record'!E12*'Order Record'!F12 -> 50292
E14: Discount: | F14: =INDEX('Cleaned Data'!I:I,MATCH($H$2,'Cleaned Data'!A:A,0)) -> 0 | G14: =G12*F14 -> 0
E16: Total Amount: | G16: =G12-G14 -> 50292
C18: ="Your Total amount is Rs. "&G16&" Only." -> Your Total amount is Rs. 50292 Only.
E19: Thank You...

Sheet Pivot Tables
A1: Month2 | B1: Sum of Total_Sales | D1: Category | E1: Sum of Total_Sales | F1: Sum of Profit | H1: Season | I1: Category | J1: Sum of Quantity | L1: Brand | M1: Sum of Total_Sales
A2: Jan | B2: 2766419.5 | D2: Clothing | E2: 1022503.9 | F2: 187590.35 | H2: Monsoon | I2: Footwear | J2: 265 | L2: Godrej Interio | M2: 3769531.5
A3: Feb | B3: 3168947.8 | D3: Electronics | E3: 8986284.7 | F3: 2328040.2 | H3: Monsoon | I3: Furniture | J3: 203 | L3: HomeTown | M3: 3352451.4 | P3: Category | Q3: Sum of Total_Sales | R3: Sum of Profit
A4: Mar | B4: 2836240.1 | D4: Footwear | E4: 1171142 | F4: 219906.86 | H4: Monsoon | I4: Electronics | J4: 191 | L4: Ikea | M4: 4683633.2 | P4: Clothing | Q4: 1022503.9 | R4: 187590.35
A5: Apr | B5: 2103874.3 | D5: Furniture | E5: 14154980 | F5: 4149124.9 | H5: Monsoon | I5: Clothing | J5: 190 | L5: Nilkamal | M5: 2349363.5 | P5: Electronics | Q5: 8986284.7 | R5: 2328040.2
A6: May | B6: 3194802 | D6: Home Appliance | E6: 6762789 | F6: 2003335.6 | H6: Monsoon | I6: Home Appliance | J6: 142 | L6: Samsung | M6: 3554384.8 | P6: Footwear | Q6: 1171142 | R6: 219906.86
A7: Jun | B7: 3059869.7 | H7: Summer | I7: Furniture | J7: 232 | P7: Furniture | Q7: 14154980 | R7: 4149124.9
A8: Jul | B8: 2129915.4 | H8: Summer | I8: Electronics | J8: 187 | P8: Home Appliance | Q8: 6762789 | R8: 2003335.6
A9: Aug | B9: 2445305.1 | H9: Summer | I9: Clothing | J9: 149
A10: Sep | B10: 2644540.9 | H10: Summer | I10: Home Appliance | J10: 135
A11: Oct | B11: 3370594.6 | H11: Summer | I11: Footwear | J11: 74 | L11: Brand | M11: Sum of Profit
A12: Nov | B12: 2586855.5 | H12: Winter | I12: Clothing | J12: 365 | L12: Godrej Interio | M12: 1319336
A13: Dec | B13: 1790334.3 | E13: Brand_Type | F13: Count of Order_ID | H13: Winter | I13: Furniture | J13: 231 | L13: HomeTown | M13: 838112.79
E14: Budget | F14: 218 | H14: Winter | I14: Home Appliance | J14: 147 | L14: Ikea | M14: 1639271.6
E15: Premium | F15: 366 | H15: Winter | I15: Electronics | J15: 124 | L15: LG | M15: 765914.54
A16: Season | B16: Average of Days_to_Deliver | E16: Standard | F16: 192 | H16: Winter | I16: Footwear | J16: 92 | L16: Samsung | M16: 1244034.6
A17: Monsoon | B17: 6.1913357
A18: Summer | B18: 5.8818898
A19: Winter | B19: 5.9632653

Sheet Dashboard
A1: E-COMMERCE SALES PERFORMANCE DASHBOARD
B5: Total Sales | D5: Total Profits | F5: Total Quantity Sold | H5: Average Discount | J5: Average Days to Deliver
B6: 32097699 | D6: 8887997.9 | F6: 2727 | H6: 0.15322165 | J6: 6.0180412
